{"@t":"2019-08-17T19:04:23.2659579Z","@mt":"{StartMessage} [Timing {TimingId}]","StartMessage":"Booting Umbraco 8.0.2.","TimingId":"720e7d5","SourceContext":"Umbraco.Core.Runtime.CoreRuntime","ProcessId":16320,"ProcessName":"iisexpress","ThreadId":1,"AppDomainId":2,"AppDomainAppId":"LMW3SVC2ROOT","MachineName":"KRISTEN-PC","Log4NetLevel":"INFO ","HttpRequestNumber":1,"HttpRequestId":"e822888b-f769-4c14-81e3-5ed413e5d594"}
{"@t":"2019-08-17T19:04:23.3029574Z","@mt":"Booting site '{HostingSiteName}', app '{HostingApplicationID}', path '{HostingPhysicalPath}', server '{MachineName}'.","HostingSiteName":"BoulderProject-Umbraco","HostingApplicationID":"/LM/W3SVC/2/ROOT","HostingPhysicalPath":"C:\\Users\\User\\Source\\Repos\\boulder_project\\BoulderProject-Umbraco\\","MachineName":"KRISTEN-PC","SourceContext":"Umbraco.Core.Runtime.CoreRuntime","ProcessId":16320,"ProcessName":"iisexpress","ThreadId":1,"AppDomainId":2,"AppDomainAppId":"LMW3SVC2ROOT","Log4NetLevel":"INFO ","HttpRequestNumber":1,"HttpRequestId":"e822888b-f769-4c14-81e3-5ed413e5d594"}
{"@t":"2019-08-17T19:04:23.6949465Z","@mt":"Acquiring.","SourceContext":"Umbraco.Core.MainDom","ProcessId":16320,"ProcessName":"iisexpress","ThreadId":1,"AppDomainId":2,"AppDomainAppId":"LMW3SVC2ROOT","MachineName":"KRISTEN-PC","Log4NetLevel":"INFO ","HttpRequestNumber":1,"HttpRequestId":"e822888b-f769-4c14-81e3-5ed413e5d594"}
{"@t":"2019-08-17T19:04:23.6979453Z","@mt":"Acquired.","SourceContext":"Umbraco.Core.MainDom","ProcessId":16320,"ProcessName":"iisexpress","ThreadId":1,"AppDomainId":2,"AppDomainAppId":"LMW3SVC2ROOT","MachineName":"KRISTEN-PC","Log4NetLevel":"INFO ","HttpRequestNumber":1,"HttpRequestId":"e822888b-f769-4c14-81e3-5ed413e5d594"}
{"@t":"2019-08-17T19:04:24.8279117Z","@mt":"{StartMessage} [Timing {TimingId}]","StartMessage":"Resolving composer types.","TimingId":"2afb389","SourceContext":"Umbraco.Core.Runtime.CoreRuntime","ProcessId":16320,"ProcessName":"iisexpress","ThreadId":1,"AppDomainId":2,"AppDomainAppId":"LMW3SVC2ROOT","MachineName":"KRISTEN-PC","Log4NetLevel":"INFO ","HttpRequestNumber":1,"HttpRequestId":"e822888b-f769-4c14-81e3-5ed413e5d594"}
{"@t":"2019-08-17T19:04:24.9659074Z","@mt":"{EndMessage} ({Duration}ms) [Timing {TimingId}]","EndMessage":"Resolved.","Duration":137,"TimingId":"2afb389","SourceContext":"Umbraco.Core.Runtime.CoreRuntime","ProcessId":16320,"ProcessName":"iisexpress","ThreadId":1,"AppDomainId":2,"AppDomainAppId":"LMW3SVC2ROOT","MachineName":"KRISTEN-PC","Log4NetLevel":"INFO ","HttpRequestNumber":1,"HttpRequestId":"e822888b-f769-4c14-81e3-5ed413e5d594"}
{"@t":"2019-08-17T19:04:36.5918559Z","@mt":"Profiler is VoidProfiler, not profiling (must run debug mode to profile).","SourceContext":"Umbraco.Web.Logging.WebProfilerComponent","ProcessId":16320,"ProcessName":"iisexpress","ThreadId":1,"AppDomainId":2,"AppDomainAppId":"LMW3SVC2ROOT","MachineName":"KRISTEN-PC","Log4NetLevel":"INFO ","HttpRequestNumber":1,"HttpRequestId":"e822888b-f769-4c14-81e3-5ed413e5d594"}
{"@t":"2019-08-17T19:04:37.2908354Z","@mt":"Initializing Umbraco internal event handlers for cache refreshing.","SourceContext":"Umbraco.Web.Cache.DistributedCacheBinderComponent","ProcessId":16320,"ProcessName":"iisexpress","ThreadId":1,"AppDomainId":2,"AppDomainAppId":"LMW3SVC2ROOT","MachineName":"KRISTEN-PC","Log4NetLevel":"INFO ","HttpRequestNumber":1,"HttpRequestId":"e822888b-f769-4c14-81e3-5ed413e5d594"}
{"@t":"2019-08-17T19:04:37.3378350Z","@mt":"Adding examine event handlers for {RegisteredIndexers} index providers.","RegisteredIndexers":3,"SourceContext":"Umbraco.Web.Search.ExamineComponent","ProcessId":16320,"ProcessName":"iisexpress","ThreadId":1,"AppDomainId":2,"AppDomainAppId":"LMW3SVC2ROOT","MachineName":"KRISTEN-PC","Log4NetLevel":"INFO ","HttpRequestNumber":1,"HttpRequestId":"e822888b-f769-4c14-81e3-5ed413e5d594"}
{"@t":"2019-08-17T19:04:37.3398347Z","@mt":"Starting initialize async background thread.","SourceContext":"Umbraco.Web.Search.ExamineComponent","ProcessId":16320,"ProcessName":"iisexpress","ThreadId":1,"AppDomainId":2,"AppDomainAppId":"LMW3SVC2ROOT","MachineName":"KRISTEN-PC","Log4NetLevel":"INFO ","HttpRequestNumber":1,"HttpRequestId":"e822888b-f769-4c14-81e3-5ed413e5d594"}
{"@t":"2019-08-17T19:04:37.4378307Z","@mt":"No last synced Id found, this generally means this is a new server/install. The server will build its caches and indexes, and then adjust its last synced Id to the latest found in the database and maintain cache updates based on that Id.","@l":"Warning","SourceContext":"Umbraco.Core.Sync.DatabaseServerMessenger","ProcessId":16320,"ProcessName":"iisexpress","ThreadId":1,"AppDomainId":2,"AppDomainAppId":"LMW3SVC2ROOT","MachineName":"KRISTEN-PC","Log4NetLevel":"WARN ","HttpRequestNumber":1,"HttpRequestId":"e822888b-f769-4c14-81e3-5ed413e5d594"}
{"@t":"2019-08-17T19:04:38.0028145Z","@mt":"Call was made to RebuildIndexes but the task runner for rebuilding is already running","@l":"Warning","SourceContext":"Umbraco.Web.Search.ExamineComponent","ProcessId":16320,"ProcessName":"iisexpress","ThreadId":1,"AppDomainId":2,"AppDomainAppId":"LMW3SVC2ROOT","MachineName":"KRISTEN-PC","Log4NetLevel":"WARN ","HttpRequestNumber":1,"HttpRequestId":"e822888b-f769-4c14-81e3-5ed413e5d594"}
{"@t":"2019-08-17T19:04:38.1048122Z","@mt":"{EndMessage} ({Duration}ms) [Timing {TimingId}]","EndMessage":"Booted.","Duration":14847,"TimingId":"720e7d5","SourceContext":"Umbraco.Core.Runtime.CoreRuntime","ProcessId":16320,"ProcessName":"iisexpress","ThreadId":1,"AppDomainId":2,"AppDomainAppId":"LMW3SVC2ROOT","MachineName":"KRISTEN-PC","Log4NetLevel":"INFO ","HttpRequestNumber":1,"HttpRequestId":"e822888b-f769-4c14-81e3-5ed413e5d594"}
{"@t":"2019-08-17T19:04:38.4608003Z","@mt":"New url {Url} detected, re-discovering application url.","Url":"http://localhost:55135/umbraco","SourceContext":"Umbraco.Core.Sync.ApplicationUrlHelper","ProcessId":16320,"ProcessName":"iisexpress","ThreadId":12,"AppDomainId":2,"AppDomainAppId":"LMW3SVC2ROOT","MachineName":"KRISTEN-PC","Log4NetLevel":"INFO ","HttpRequestNumber":2,"HttpRequestId":"c72cc261-35ee-4b15-bee9-3f3e2d105df5"}
{"@t":"2019-08-17T19:04:38.4618001Z","@mt":"ApplicationUrl: {UmbracoAppUrl} (UmbracoModule request)","UmbracoAppUrl":"http://localhost:55135/umbraco","SourceContext":"Umbraco.Core.Sync.ApplicationUrlHelper","ProcessId":16320,"ProcessName":"iisexpress","ThreadId":12,"AppDomainId":2,"AppDomainAppId":"LMW3SVC2ROOT","MachineName":"KRISTEN-PC","Log4NetLevel":"INFO ","HttpRequestNumber":2,"HttpRequestId":"c72cc261-35ee-4b15-bee9-3f3e2d105df5"}
